Metadata-Version: 1.0
Name: utils-distributions
Version: 0.1
Summary: Gaussian distributions
Home-page: UNKNOWN
Author: Irune Lansorena
Author-email: UNKNOWN
License: UNKNOWN
Platform: UNKNOWN
